NotionInterface/__init__.py
NotionInterface/constants.py
NotionInterface/notion_database.py
NotionInterface/notion_database_types.py
NotionInterface/notion_header.py
NotionInterface/notion_page.py
NotionInterface-0.0.6.dist-info/METADATA
NotionInterface-0.0.6.dist-info/WHEEL
NotionInterface-0.0.6.dist-info/top_level.txt
NotionInterface-0.0.6.dist-info/RECORD
