Metadata-Version: 2.1
Name: NotionInterface
Version: 0.0.6
Summary: A simple Notion db interface for Python
Home-page: UNKNOWN
Author: LukaPedra (Lucca Rocha)
Author-email: <lucca.v.rocha@gmail.com>
License: UNKNOWN
Keywords: python,Notion,Database,page,Block,pandas
Platform: UNKNOWN
Classifier: Development Status :: 1 - Planning
Classifier: Intended Audience :: Developers
Classifier: Programming Language :: Python :: 3
Classifier: Operating System :: Unix
Classifier: Operating System :: MacOS :: MacOS X
Classifier: Operating System :: Microsoft :: Windows
Requires-Dist: certifi (==2022.12.7)
Requires-Dist: charset-normalizer (==3.1.0)
Requires-Dist: idna (==3.4)
Requires-Dist: requests (==2.28.2)
Requires-Dist: urllib3 (==1.26.15)
Requires-Dist: pandas
Requires-Dist: openpyxl
